audiorecorder/__init__.py
audiorecorder/frontend/build/asset-manifest.json
audiorecorder/frontend/build/bootstrap.min.css
audiorecorder/frontend/build/index.html
audiorecorder/frontend/build/static/js/538.ed8de53c.chunk.js
audiorecorder/frontend/build/static/js/538.ed8de53c.chunk.js.map
audiorecorder/frontend/build/static/js/850.047e6c02.chunk.js
audiorecorder/frontend/build/static/js/850.047e6c02.chunk.js.map
audiorecorder/frontend/build/static/js/main.c28cbcfe.js
audiorecorder/frontend/build/static/js/main.c28cbcfe.js.LICENSE.txt
audiorecorder/frontend/build/static/js/main.c28cbcfe.js.map
streamlit-rec/__init__.py
streamlit-rec/streamlit_rec.py
streamlit_rec/__init__.py
streamlit_rec/streamlit_rec.py
streamlit_rec/frontend/build/asset-manifest.json
streamlit_rec/frontend/build/bootstrap.min.css
streamlit_rec/frontend/build/index.html
streamlit_rec/frontend/build/static/js/538.b60755be.chunk.js
streamlit_rec/frontend/build/static/js/538.b60755be.chunk.js.map
streamlit_rec/frontend/build/static/js/538.ed8de53c.chunk.js
streamlit_rec/frontend/build/static/js/538.ed8de53c.chunk.js.map
streamlit_rec/frontend/build/static/js/850.047e6c02.chunk.js
streamlit_rec/frontend/build/static/js/850.047e6c02.chunk.js.map
streamlit_rec/frontend/build/static/js/main.18f687d8.js
streamlit_rec/frontend/build/static/js/main.18f687d8.js.LICENSE.txt
streamlit_rec/frontend/build/static/js/main.18f687d8.js.map
streamlit_rec/frontend/build/static/js/main.c28cbcfe.js
streamlit_rec/frontend/build/static/js/main.c28cbcfe.js.LICENSE.txt
streamlit_rec/frontend/build/static/js/main.c28cbcfe.js.map
streamlit_rec-0.0.5.dist-info/LICENSE
streamlit_rec-0.0.5.dist-info/METADATA
streamlit_rec-0.0.5.dist-info/WHEEL
streamlit_rec-0.0.5.dist-info/top_level.txt
streamlit_rec-0.0.5.dist-info/RECORD
