Metadata-Version: 2.1
Name: streamlit_rec
Version: 0.0.5
Summary: Audio recorder component for streamlit
Home-page: 
Author: Benson Sung
Author-email: 
Requires-Python: >=3.6
License-File: LICENSE
Requires-Dist: streamlit >=0.63
Requires-Dist: pydub >=0.24
